azure/mgmt/planetarycomputer/__init__.py
azure/mgmt/planetarycomputer/_client.py
azure/mgmt/planetarycomputer/_configuration.py
azure/mgmt/planetarycomputer/_patch.py
azure/mgmt/planetarycomputer/_validation.py
azure/mgmt/planetarycomputer/_version.py
azure/mgmt/planetarycomputer/py.typed
azure/mgmt/planetarycomputer/_utils/__init__.py
azure/mgmt/planetarycomputer/_utils/model_base.py
azure/mgmt/planetarycomputer/_utils/serialization.py
azure/mgmt/planetarycomputer/aio/__init__.py
azure/mgmt/planetarycomputer/aio/_client.py
azure/mgmt/planetarycomputer/aio/_configuration.py
azure/mgmt/planetarycomputer/aio/_patch.py
azure/mgmt/planetarycomputer/aio/operations/__init__.py
azure/mgmt/planetarycomputer/aio/operations/_operations.py
azure/mgmt/planetarycomputer/aio/operations/_patch.py
azure/mgmt/planetarycomputer/models/__init__.py
azure/mgmt/planetarycomputer/models/_enums.py
azure/mgmt/planetarycomputer/models/_models.py
azure/mgmt/planetarycomputer/models/_patch.py
azure/mgmt/planetarycomputer/operations/__init__.py
azure/mgmt/planetarycomputer/operations/_operations.py
azure/mgmt/planetarycomputer/operations/_patch.py
azure_mgmt_planetarycomputer-1.0.0b1.dist-info/LICENSE
azure_mgmt_planetarycomputer-1.0.0b1.dist-info/METADATA
azure_mgmt_planetarycomputer-1.0.0b1.dist-info/WHEEL
azure_mgmt_planetarycomputer-1.0.0b1.dist-info/top_level.txt
azure_mgmt_planetarycomputer-1.0.0b1.dist-info/RECORD
